<?xml version="1.0" encoding="UTF-8"?>

<Patient xmlns="http://hl7.org/fhir">
  <id value="SUfferer"/>
  <meta>
    <profile value="http://fhir.ch/ig/ch-core/StructureDefinition/ch-core-patient"/>
  </meta>
  <text>
    <status value="generated"/><div xmlns="http://www.w3.org/1999/xhtml"><p><b>Generated Narrative</b></p><p><b>name</b>: Samuel Ufferer </p><p><b>telecom</b>: <a href="tel:+41799999999">+41 79 999 99 99</a>, <a href="mailto:martina.muster@example.com">martina.muster@example.com</a></p><p><b>gender</b>: female</p><p><b>birthDate</b>: 1995-01-27</p><p><b>address</b>: Leidensweg 15a Bern 3000 </p></div>
  </text>
  <name>
    <family value="Ufferer"/>
    <given value="Samuel"/>
  </name>
  <telecom>
    <system value="phone"/>
    <value value="+41 79 999 99 99"/>
  </telecom>
  <telecom>
    <system value="email"/>
    <value value="martina.muster@example.com"/>
  </telecom>
  <gender value="female"/>
  <birthDate value="1995-01-27"/>
  <address>
    <line value="Leidensweg 15a"/>
    <city value="Bern"/>
    <postalCode value="3000"/>
  </address>
</Patient>